pyssc/Ssc_device.py
pyssc/Ssc_device_setup.py
pyssc/Ssc_transaction.py
pyssc/__init__.py
pyssc/scan.py
pyssc-0.0.2.dev7.dist-info/LICENSE
pyssc-0.0.2.dev7.dist-info/METADATA
pyssc-0.0.2.dev7.dist-info/WHEEL
pyssc-0.0.2.dev7.dist-info/top_level.txt
pyssc-0.0.2.dev7.dist-info/zip-safe
pyssc-0.0.2.dev7.dist-info/RECORD
